django_email_sender/__init__.py
django_email_sender/email_logger.py
django_email_sender/email_sender.py
django_email_sender/email_sender_constants.py
django_email_sender/email_sender_payload.py
django_email_sender/exceptions.py
django_email_sender/messages.py
django_email_sender/models.py
django_email_sender/translation.py
django_email_sender/utils.py
django_email_sender/validation.py
django_email_sender-2.0.6.dist-info/licenses/LICENCE
tests/__init__.py
tests/test_email_sender_models.py
tests/test_fixture.py
tests/test_functions.py
tests/test_integration_models.py
tests/test_sending_email.py
django_email_sender-2.0.6.dist-info/METADATA
django_email_sender-2.0.6.dist-info/WHEEL
django_email_sender-2.0.6.dist-info/top_level.txt
django_email_sender-2.0.6.dist-info/RECORD
