Metadata-Version: 2.4
Name: django-email-sender
Version: 2.0.6
Summary: A chainable Django email sender utility.
Home-page: https://github.com/EgbieAndersonUku1/django-email-sender
Author: Egbie Uku
Author-email: egbieuku@hotmail.com
Keywords: django,email,email-sender,html-email,plain-text-email,email-utility,rich-template,chaining,logger,logging,database-integration,email-templates,django-email
Classifier: Programming Language :: Python :: 3
Classifier: Framework :: Django
Classifier: Framework :: Django :: 3.2
Classifier: Framework :: Django :: 4.0
Classifier: Framework :: Django :: 5.0
Classifier: License :: OSI Approved :: MIT License
Classifier: Operating System :: OS Independent
Classifier: Development Status :: 5 - Production/Stable
Classifier: Intended Audience :: Developers
Classifier: Topic :: Software Development :: Libraries :: Python Modules
Requires-Python: >=3.10,<3.14
License-File: LICENCE
Requires-Dist: Django<6.0,>=3.2
Requires-Dist: requests>=2.31
Requires-Dist: beautifulsoup4>=4.13
Requires-Dist: nh3>=0.2.21
Dynamic: author
Dynamic: author-email
Dynamic: classifier
Dynamic: description
Dynamic: description-content-type
Dynamic: home-page
Dynamic: keywords
Dynamic: license-file
Dynamic: requires-dist
Dynamic: requires-python
Dynamic: summary
